jiit_marks/__init__.py
jiit_marks/extractor.py
jiit_marks-0.2.0.dist-info/LICENSE
jiit_marks-0.2.0.dist-info/METADATA
jiit_marks-0.2.0.dist-info/WHEEL
jiit_marks-0.2.0.dist-info/RECORD
