Metadata-Version: 2.1
Name: jiit-marks
Version: 0.2.0
Summary: Extract marks data from report PDF obtained from JIIT Webportal (yuck!)
License: MIT
Author: Harsh Sharma
Author-email: harsh@codelif.in
Requires-Python: >=3.9,<4.0
Classifier: License :: OSI Approved :: MIT License
Classifier: Programming Language :: Python :: 3
Classifier: Programming Language :: Python :: 3.9
Classifier: Programming Language :: Python :: 3.10
Classifier: Programming Language :: Python :: 3.11
Classifier: Programming Language :: Python :: 3.12
Classifier: Programming Language :: Python :: 3.13
Requires-Dist: pymupdf (>=1.25.0,<2.0.0)
